reflex_reflexcustomcomponent/__init__.py
reflex_reflexcustomcomponent/reflexcustomcomponent.py
reflex_reflexcustomcomponent-0.0.1.dist-info/METADATA
reflex_reflexcustomcomponent-0.0.1.dist-info/WHEEL
reflex_reflexcustomcomponent-0.0.1.dist-info/top_level.txt
reflex_reflexcustomcomponent-0.0.1.dist-info/RECORD
