Metadata-Version: 2.1
Name: reflex-reflexcustomcomponent
Version: 0.0.1
Summary: Reflex custom component reflexcustomcomponent
Author-email: YOUREMAIL@domain.com
License: Apache-2.0
Keywords: reflex,reflex-custom-components
Classifier: Development Status :: 4 - Beta
Requires-Python: >=3.9
Requires-Dist: reflex>=0.6.4
Provides-Extra: dev
Requires-Dist: build; extra == "dev"
Requires-Dist: twine; extra == "dev"
